{
  "@context": "https://schema.org",
  "@type": "HowTo",
  "name": "How do I disable notifications on AirSend?",
  "step": [
    {
      "@type": "HowToStep",
      "text": "Open Settings",
      "image": "modify_notifications/section_settings.jpg"
    },
    {
      "@type": "HowToStep",
      "text": "Scroll down to Notifications page",
      "image": "modify_notifications/2_notification_settings.jpg"
    },
    {
      "@type": "HowToStep",
      "text": "Toggle on/off the type of notifications you would like to receive",
      "image": "modify_notifications/3_notification_toggled.jpg"
    }
  ]
}